src/__init__.py
src/main.py
src/commands/__init__.py
src/commands/activate.py
src/commands/add.py
src/commands/change.py
src/commands/connect.py
src/commands/find.py
src/commands/list.py
src/commands/remove.py
src/commands/tunnel.py
src/commands/update.py
src/util/__init__.py
src/util/completion.py
src/util/config_util.py
ussh-0.2.3.dist-info/METADATA
ussh-0.2.3.dist-info/WHEEL
ussh-0.2.3.dist-info/entry_points.txt
ussh-0.2.3.dist-info/top_level.txt
ussh-0.2.3.dist-info/RECORD
