Metadata-Version: 2.4
Name: ussh
Version: 0.2.3
Summary: Command Line Tool to use ssh simply
Requires-Python: >=3.9.1
Requires-Dist: click>=8.1.7
Requires-Dist: tabulate>=0.9.0
